aiboxlab/__init__.py
aiboxlab-0.0.0.dist-info/METADATA
aiboxlab-0.0.0.dist-info/WHEEL
aiboxlab-0.0.0.dist-info/top_level.txt
aiboxlab-0.0.0.dist-info/RECORD
