Metadata-Version: 2.1
Name: aiboxlab
Version: 0.0.0
Summary: AIBox Lab
